{
  "application": [
    {
      "project_name": "PIC-SURE-API Build",
      "project_job_git_key":"PSA",
      "git_hash": "a179704b5c7f4a14ff2076638b8cb730732f4340"
    },{
      "project_name": "PIC-SURE-HPDS Build",
      "project_job_git_key":"PSH",
      "git_hash": "ab78f592b1c5257ab859cf5dacdff4dc69fc54ce"
    },{
      "project_name": "PIC-SURE Auth Micro-App Build",
      "project_job_git_key":"PSAMA",
      "git_hash": "8a61547e9d603691ce870222aae5a1b485fd928a"
    },{
      "project_name": "PIC-SURE-HPDS-UI Build",
      "project_job_git_key":"PSHU",
      "git_hash": "10c1942ec05da5bc2c5ad5da2b192cfd49877e07"
    },{
      "project_name": "project-specific-ui",
      "project_job_git_key":"PSU",
      "git_hash": "34f532e85643e33ce924fb142f7924278d069022"
    }
  ]
}
